{
	"ENCYCLOPEDIA_ITEM_BASE_INFO": {
		"en": "Basic Information:",
		"de": "Grundlegende Informationen:",
		"es": "Información básica:",
		"it": "Informazioni di base:",
		"da": "Grundlæggende information:",
		"nl": "Basisinformatie:",
		"fr": "Informations de base:",
		"tr": "Temel Bilgiler:",
		"ko": "기본 정보:",
		"zh": "基本信息：",
		"zh-TW": "基本資訊：",
		"ja": "基本情報：",
		"pt-BR": "Informações básicas:",
		"ru": "Основная информация:"
	},
	"ENCYCLOPEDIA_ITEM_BASE_INFO_NOTE": {
		"en": "Useful information about the selected item.",
		"de": "Nützliche Informationen über das ausgewählte Element.",
		"es": "Información útil sobre el objeto seleccionado.",
		"it": "Informazioni utili sull'oggetto selezionato.",
		"da": "Nyttig information om det valgte element.",
		"nl": "Handige informatie over het geselecteerde item.",
		"fr": "Informations utiles sur l'objet sélectionné.",
		"tr": "Seçilen öğe hakkında faydalı bilgiler.",
		"ko": "선택한 항목에 대한 유용한 정보입니다.",
		"zh": "关于所选物品的有用信息。",
		"zh-TW": "關於所選物品的有用信息。",
		"ja": "選択したアイテムに関する有用な情報。",
		"pt-BR": "Informações úteis sobre o item selecionado.",
		"ru": "Полезная информация о выбранном предмете."
	},
	"ENCYCLOPEDIA_ITEM_PATH_LBL": {
		"en": "Path:",
		"de": "Pfad:",
		"es": "Ruta:",
		"it": "Percorso:",
		"da": "Sti:",
		"nl": "Pad:",
		"fr": "Chemin:",
		"tr": "Yol:",
		"ko": "경로:",
		"zh": "路径：",
		"zh-TW": "路徑：",
		"ja": "パス：",
		"pt-BR": "Caminho:",
		"ru": "Путь:"
	},
	"ENCYCLOPEDIA_ITEM_NAME_LBL": {
		"en": "Name:",
		"de": "Name:",
		"es": "Nombre:",
		"it": "Nome:",
		"da": "Navn:",
		"nl": "Naam:",
		"fr": "Nom:",
		"tr": "Adı:",
		"ko": "이름:",
		"zh": "名称：",
		"zh-TW": "名稱：",
		"ja": "名前：",
		"pt-BR": "Nome:",
		"ru": "Имя:"
	},
	"ENCYCLOPEDIA_ITEM_TAG_LBL": {
		"en": "Tag:",
		"de": "Tag:",
		"es": "Etiqueta:",
		"it": "Tag:",
		"da": "Mærke:",
		"nl": "Tag:",
		"fr": "Étiquette:",
		"tr": "Etiket:",
		"ko": "태그:",
		"zh": "标签：",
		"zh-TW": "標籤：",
		"ja": "タグ：",
		"pt-BR": "Tag:",
		"ru": "Тег:"
	},
	"ENCYCLOPEDIA_ITEM_GROUP_LBL": {
		"en": "Group:",
		"de": "Gruppe:",
		"es": "Grupo:",
		"it": "Gruppo:",
		"da": "Gruppe:",
		"nl": "Groep:",
		"fr": "Groupe:",
		"tr": "Grup:",
		"ko": "그룹:",
		"zh": "组：",
		"zh-TW": "組：",
		"ja": "グループ：",
		"pt-BR": "Grupo:",
		"ru": "Группа:"
	},
	"ENCYCLOPEDIA_ITEM_DESCRIPTION_LBL": {
		"en": "Description:",
		"de": "Beschreibung:",
		"es": "Descripción:",
		"it": "Descrizione:",
		"da": "Beskrivelse:",
		"nl": "Beschrijving:",
		"fr": "Description:",
		"tr": "Açıklama:",
		"ko": "설명:",
		"zh": "描述：",
		"zh-TW": "描述：",
		"ja": "説明：",
		"pt-BR": "Descrição:",
		"ru": "Описание:"
	},
	"ENCYCLOPEDIA_ITEM_STACK_SIZE_LBL": {
		"en": "Stack Size:",
		"de": "Stapelgröße:",
		"es": "Tamaño de pila:",
		"it": "Dimensione dello stack:",
		"da": "Stakstørrelse:",
		"nl": "Stapelgrootte:",
		"fr": "Taille de la pile:",
		"tr": "Yığın Boyutu:",
		"ko": "스택 크기:",
		"zh": "堆叠大小：",
		"zh-TW": "堆疊大小：",
		"ja": "スタックサイズ：",
		"pt-BR": "Tamanho da pilha:",
		"ru": "Размер стека:"
	},
	"ENCYCLOPEDIA_ITEM_CAN_BE_BLUEPRINT_LBL": {
		"en": "Can be Blueprint:",
		"de": "Kann ein Blueprint sein:",
		"es": "Puede ser un plano:",
		"it": "Può essere un progetto:",
		"da": "Kan være en blueprint:",
		"nl": "Kan een blauwdruk zijn:",
		"fr": "Peut être un plan:",
		"tr": "Blueprint olabilir:",
		"ko": "블루프린트가 될 수 있습니다:",
		"zh": "可以是蓝图：",
		"zh-TW": "可以是藍圖：",
		"ja": "ブループリントになる可能性があります：",
		"pt-BR": "Pode ser um projeto:",
		"ru": "Может быть чертежом:"
	},
	"ENCYCLOPEDIA_ITEM_CAN_BE_PAINTED_LBL": {
		"en": "Can be Painted:",
		"de": "Kann bemalt werden:",
		"es": "Puede ser pintado:",
		"it": "Può essere dipinto:",
		"da": "Kan males:",
		"nl": "Kan worden geverfd:",
		"fr": "Peut être peint:",
		"tr": "Boyayabilir:",
		"ko": "칠할 수 있습니다:",
		"zh": "可以涂色：",
		"zh-TW": "可以塗色：",
		"ja": "塗装可能：",
		"pt-BR": "Pode ser pintado:",
		"ru": "Может быть покрашен:"
	},
	"ENCYCLOPEDIA_ITEM_USES_STATS_LBL": {
		"en": "Uses Stats:",
		"de": "Verwendet Statistiken:",
		"es": "Usa estadísticas:",
		"it": "Usa statistiche:",
		"da": "Bruger statistikker:",
		"nl": "Gebruikt statistieken:",
		"fr": "Utilise des statistiques:",
		"tr": "İstatistikleri Kullanır:",
		"ko": "통계 사용:",
		"zh": "使用统计数据：",
		"zh-TW": "使用統計數據：",
		"ja": "統計を使用：",
		"pt-BR": "Usa estatísticas:",
		"ru": "Использует статистику:"
	},
	"ENCYCLOPEDIA_ITEM_CAN_BE_TAMED_LBL": {
		"en": "Can be Tamed:",
		"de": "Kann gezähmt werden:",
		"es": "Puede ser domesticado:",
		"it": "Può essere addomesticato:",
		"da": "Kan tæmmes:",
		"nl": "Kan getemd worden:",
		"fr": "Peut être apprivoisé:",
		"tr": "Evcilleştirilebilir:",
		"ko": "길들일 수 있습니다:",
		"zh": "可以被驯服：",
		"zh-TW": "可以被馴服：",
		"ja": "飼いならすことができます：",
		"pt-BR": "Pode ser domado:",
		"ru": "Может быть приручен:"
	},
	"ENCYCLOPEDIA_ITEM_IS_KNOCK_TAME_LBL": {
		"en": "Is Knock Tame:",
		"de": "Ist Knock Tame:",
		"es": "Es Knock Tame:",
		"it": "È Knock Tame:",
		"da": "Er Knock Tame:",
		"nl": "Is Knock Tame:",
		"fr": "Est Knock Tame:",
		"tr": "Knock Tame'dir:",
		"ko": "녹 테임입니다:",
		"zh": "是Knock Tame：",
		"zh-TW": "是Knock Tame：",
		"ja": "ノックテイムです：",
		"pt-BR": "É Knock Tame:",
		"ru": "Это Knock Tame:"
	},
	"ENCYCLOPEDIA_ITEM_IS_PASSIVE_TAME_LBL": {
		"en": "Is Passive Tame:",
		"de": "Ist Passiv Tame:",
		"es": "Es un tiro pasivo:",
		"it": "È un tiro passivo:",
		"da": "Er en passiv tæmning:",
		"nl": "Is een passieve taming:",
		"fr": "Est un apprivoisement passif:",
		"tr": "Pasif Tame'dir:",
		"ko": "수동 테임입니다:",
		"zh": "是被动驯服：",
		"zh-TW": "是被動馴服：",
		"ja": "受動的なテイムです：",
		"pt-BR": "É um tiro passivo:",
		"ru": "Это пассивное приручение:"
	},
	"ENCYCLOPEDIA_ITEM_IS_SPECIAL_TAME_LBL": {
		"en": "Is Special Tame:",
		"de": "Ist Spezial Tame:",
		"es": "Es un tiro especial:",
		"it": "È un tiro speciale:",
		"da": "Er en speciel tæmning:",
		"nl": "Is een speciale taming:",
		"fr": "Est un apprivoisement spécial:",
		"tr": "Özel Tame'dir:",
		"ko": "특별한 테임입니다:",
		"zh": "是特殊驯服：",
		"zh-TW": "是特殊馴服：",
		"ja": "特別なテイムです：",
		"pt-BR": "É um tiro especial:",
		"ru": "Это специальное приручение:"
	},
	"ENCYCLOPEDIA_ITEM_CAN_BREED_LBL": {
		"en": "Can Breed:",
		"de": "Kann züchten:",
		"es": "Puede criar:",
		"it": "Può riprodursi:",
		"da": "Kan avle:",
		"nl": "Kan fokken:",
		"fr": "Peut se reproduire:",
		"tr": "Üreyebilir:",
		"ko": "번식할 수 있습니다:",
		"zh": "可以繁殖：",
		"zh-TW": "可以繁殖：",
		"ja": "繁殖可能：",
		"pt-BR": "Pode se reproduzir:",
		"ru": "Может размножаться:"
	},
	"ENCYCLOPEDIA_ITEM_IS_FLAYER_LBL": {
		"en": "Is Flayer:",
		"de": "Ist Flayer:",
		"es": "Es Flayer:",
		"it": "È Flayer:",
		"da": "Er Flayer:",
		"nl": "Is Flayer:",
		"fr": "Est Flayer:",
		"tr": "Flayer'dir:",
		"ko": "플레이어입니다:",
		"zh": "是Flayer：",
		"zh-TW": "是Flayer：",
		"ja": "フレイヤーです：",
		"pt-BR": "É Flayer:",
		"ru": "Это Flayer:"
	},
	"ENCYCLOPEDIA_ITEM_IS_WATER_DINO_LBL": {
		"en": "Is Water Dino:",
		"de": "Ist Wasser Dino:",
		"es": "Es un dinosaurio acuático:",
		"it": "È un dinosauro d'acqua:",
		"da": "Er en vanddino:",
		"nl": "Is een waterdino:",
		"fr": "Est un dino d'eau:",
		"tr": "Su Dino'su:",
		"ko": "물 공룡입니다:",
		"zh": "是水恐龙：",
		"zh-TW": "是水恐龍：",
		"ja": "水恐竜です：",
		"pt-BR": "É um dinossauro aquático:",
		"ru": "Это водный динозавр:"
	},
	"ENCYCLOPEDIA_ITEM_TAMING_INFO": {
		"en": "Taming Information:",
		"de": "Zähmungsinformationen:",
		"es": "Información de domesticación:",
		"it": "Informazioni sul domare:",
		"da": "Tæmning information:",
		"nl": "Tamingsinformatie:",
		"fr": "Informations de dressage:",
		"tr": "Evcilleştirme Bilgisi:",
		"ko": "조련 정보:",
		"zh": "驯服信息：",
		"zh-TW": "馴服資訊：",
		"ja": "テイム情報：",
		"pt-BR": "Informações de domesticação:",
		"ru": "Информация о приручении:"
	},
	"ENCYCLOPEDIA_ITEM_TAMING_INFO_NOTE": {
		"en": "Taming information about the selected dino.",
		"de": "Zähmungsinformationen über das ausgewählte Dino.",
		"es": "Información de domesticación sobre el dino seleccionado.",
		"it": "Informazioni sul domare del dinosauro selezionato.",
		"da": "Tæmning information om den valgte dino.",
		"nl": "Tamingsinformatie over de geselecteerde dino.",
		"fr": "Informations de dressage sur le dino sélectionné.",
		"tr": "Seçilen dino hakkında evcilleştirme bilgisi.",
		"ko": "선택한 공룡에 대한 조련 정보입니다.",
		"zh": "关于所选恐龙的驯服信息。",
		"zh-TW": "關於所選恐龍的馴服資訊。",
		"ja": "選択した恐竜に関するテイム情報。",
		"pt-BR": "Informações de domesticação sobre o dinossauro selecionado.",
		"ru": "Информация о приручении выбранного динозавра."
	},
	"ENCYCLOPEDIA_ITEM_TAMING_INFO_INACCURACY": {
		"en": "The taming information may not be 100% accurate as some dinos use custom logic that can't be detected by Ark-Nucleus.",
		"de": "Die Zähmungsinformationen sind möglicherweise nicht zu 100% korrekt, da einige Dinos benutzerdefinierte Logik verwenden, die von Ark-Nucleus nicht erkannt werden kann.",
		"es": "La información de domesticación puede no ser 100% precisa, ya que algunos dinos utilizan lógica personalizada que no puede ser detectada por Ark-Nucleus.",
		"it": "Le informazioni sul domare potrebbero non essere al 100% accurate in quanto alcuni dinosauro utilizzano logiche personalizzate che non possono essere rilevate da Ark-Nucleus.",
		"da": "Tæmningsoplysningerne er muligvis ikke 100% nøjagtige, da nogle dinoer bruger brugerdefineret logik, der ikke kan registreres af Ark-Nucleus.",
		"nl": "De tamingsinformatie is mogelijk niet 100% nauwkeurig, omdat sommige dinos gebruikmaken van aangepaste logica die niet kan worden gedetecteerd door Ark-Nucleus.",
		"fr": "Les informations de dressage peuvent ne pas être à 100% précises, car certains dinos utilisent une logique personnalisée qui ne peut pas être détectée par Ark-Nucleus.",
		"tr": "Evcilleştirme bilgisi %100 doğru olmayabilir, çünkü bazı dinozorlar Ark-Nucleus tarafından algılanamayan özel mantık kullanır.",
		"ko": "조련 정보는 100% 정확하지 않을 수 있습니다. 일부 공룡은 Ark-Nucleus에서 감지할 수 없는 사용자 정의 로직을 사용합니다.",
		"zh": "驯服信息可能不是100%准确的，因为一些恐龙使用了无法被Ark-Nucleus检测到的自定义逻辑。",
		"zh-TW": "馴服資訊可能不是100%準確的，因為一些恐龍使用了無法被Ark-Nucleus檢測到的自定邏輯。",
		"ja": "テイム情報は100%正確でない場合があります。一部の恐竜はArk-Nucleusで検出できないカスタムロジックを使用しています。",
		"pt-BR": "As informações de domesticação podem não ser 100% precisas, pois alguns dinossauros usam lógica personalizada que não pode ser detectada pelo Ark-Nucleus.",
		"ru": "Информация о приручении может быть не 100% точной, так как некоторые динозавры используют пользовательскую логику, которую нельзя обнаружить Ark-Nucleus."
	},
	"ENCYCLOPEDIA_ITEM_TAMING_SPECIAL_WARNING": {
		"en": "This dino is likely to have special taming requirements. Please consult an external source for more information.",
		"de": "Dieser Dino hat wahrscheinlich spezielle Zähmanforderungen. Bitte konsultieren Sie eine externe Quelle für weitere Informationen.",
		"es": "Es probable que este dino tenga requisitos de domesticación especiales. Consulte una fuente externa para obtener más información.",
		"it": "Questo dinosauro probabilmente ha requisiti di domare speciali. Consultare una fonte esterna per ulteriori informazioni.",
		"da": "Denne dino har sandsynligvis specielle tæmningskrav. Konsulter en ekstern kilde for mere information.",
		"nl": "Deze dino heeft waarschijnlijk speciale tamingsvereisten. Raadpleeg een externe bron voor meer informatie.",
		"fr": "Ce dino a probablement des exigences de dressage spéciales. Veuillez consulter une source externe pour plus d'informations.",
		"tr": "Bu dinozorun özel evcilleştirme gereksinimleri olabilir. Daha fazla bilgi için lütfen harici bir kaynağa danışın.",
		"ko": "이 공룡은 특별한 조련 요구 사항을 가질 가능성이 높습니다. 자세한 정보는 외부 소스를 참조하십시오.",
		"zh": "这个恐龙可能有特殊的驯服要求。请咨询外部来源以获取更多信息。",
		"zh-TW": "這個恐龍可能有特殊的馴服要求。請諮詢外部來源以獲取更多信息。",
		"ja": "この恐竜は特別なテイム要件を持っている可能性があります。詳細な情報については外部ソースを参照してください。",
		"pt-BR": "Este dinossauro provavelmente tem requisitos de domesticação especiais. Consulte uma fonte externa para obter mais informações.",
		"ru": "У этого динозавра, вероятно, есть специальные требования к приручению. Пожалуйста, обратитесь к внешнему источнику для получения дополнительной информации."
	},
	"ENCYCLOPEDIA_ITEM_TAMING_MULTIPLIER_LBL": {
		"en": "Taming Multiplier:",
		"de": "Zähmungs-Multiplikator:",
		"es": "Multiplicador de domesticación:",
		"it": "Moltiplicatore di domare:",
		"da": "Tæmningsmultiplikator:",
		"nl": "Tamingsvermenigvuldiger:",
		"fr": "Multiplicateur de dressage:",
		"tr": "Evcilleştirme Çarpanı:",
		"ko": "조련 배수:",
		"zh": "驯服乘数：",
		"zh-TW": "馴服乘數：",
		"ja": "テイム乗数：",
		"pt-BR": "Multiplicador de domesticação:",
		"ru": "Множитель приручения:"
	},
	"ENCYCLOPEDIA_ITEM_TAMING_FOOD_LBL": {
		"en": "Taming Food:",
		"de": "Zähmungsfutter:",
		"es": "Comida de domesticación:",
		"it": "Cibo per domare:",
		"da": "Tæmningsmad:",
		"nl": "Tamingsvoedsel:",
		"fr": "Nourriture de dressage:",
		"tr": "Evcilleştirme Yiyeceği:",
		"ko": "조련 음식:",
		"zh": "驯服食物：",
		"zh-TW": "馴服食物：",
		"ja": "テイムフード：",
		"pt-BR": "Comida de domesticação:",
		"ru": "Приручение еды:"
	},
	"ENCYCLOPEDIA_ITEM_TAMING_FOOD_NOTE": {
		"en": "The food required to tame the selected dino.",
		"de": "Das Futter, das benötigt wird, um den ausgewählten Dino zu zähmen.",
		"es": "La comida necesaria para domesticar el dino seleccionado.",
		"it": "Il cibo richiesto per domare il dinosauro selezionato.",
		"da": "Mad, der kræves for at tæmme den valgte dino.",
		"nl": "Het voedsel dat nodig is om de geselecteerde dino te temmen.",
		"fr": "La nourriture nécessaire pour apprivoiser le dino sélectionné.",
		"tr": "Seçilen dino'yu evcilleştirmek için gereken yiyecek.",
		"ko": "선택한 공룡을 길들이기 위해 필요한 음식입니다.",
		"zh": "驯服所选恐龙所需的食物。",
		"zh-TW": "馴服所選恐龍所需的食物。",
		"ja": "選択した恐竜をテイムするために必要な食べ物。",
		"pt-BR": "O alimento necessário para domar o dinossauro selecionado.",
		"ru": "Еда, необходимая для приручения выбранного динозавра."
	},
	"ENCYCLOPEDIA_ITEM_DAMAGE_MULTIPLIER_LBL": {
		"en": "Damage Multiplier:",
		"de": "Schadensmultiplikator:",
		"es": "Multiplicador de daño:",
		"it": "Moltiplicatore di danni:",
		"da": "Skademultiplikator:",
		"nl": "Schadevermenigvuldiger:",
		"fr": "Multiplicateur de dégâts:",
		"tr": "Hasar Çarpanı:",
		"ko": "피해 배수:",
		"zh": "伤害乘数：",
		"zh-TW": "傷害乘數：",
		"ja": "ダメージ乗数：",
		"pt-BR": "Multiplicador de dano:",
		"ru": "Множитель урона:"
	},
	"ENCYCLOPEDIA_ITEM_DAMAGE_MULTIPLIER_NOTE": {
		"en": "The bone damage multiplier of the selected dino.",
		"de": "Der Knochen-Schadensmultiplikator des ausgewählten Dino.",
		"es": "El multiplicador de daño óseo del dino seleccionado.",
		"it": "Il moltiplicatore del danno osseo del dinosauro selezionato.",
		"da": "Knogleskademultiplikatoren af den valgte dino.",
		"nl": "De bot schadevermenigvuldiger van de geselecteerde dino.",
		"fr": "Le multiplicateur de dégâts osseux du dino sélectionné.",
		"tr": "Seçilen dino'nun kemik hasar çarpanı.",
		"ko": "선택한 공룡의 뼈 피해 배수입니다.",
		"zh": "所选恐龙的骨伤害乘数。",
		"zh-TW": "所選恐龍的骨傷害乘數。",
		"ja": "選択した恐竜の骨ダメージ乗数。",
		"pt-BR": "O multiplicador de dano ósseo do dinossauro selecionado.",
		"ru": "Множитель костей повреждения выбранного динозавра."
	},
	"ENCYCLOPEDIA_ITEM_CRAFTING_INFO": {
		"en": "Crafting Information:",
		"de": "Herstellungsinformationen:",
		"es": "Información de elaboración:",
		"it": "Informazioni sulla creazione:",
		"da": "Håndværksoplysninger:",
		"nl": "Maak informatie:",
		"fr": "Informations de fabrication:",
		"tr": "Üretim Bilgisi:",
		"ko": "제작 정보:",
		"zh": "制作信息：",
		"zh-TW": "製作信息：",
		"ja": "クラフト情報：",
		"pt-BR": "Informações de fabricação:",
		"ru": "Информация о создании:"
	},
	"ENCYCLOPEDIA_ITEM_CRAFTING_INFO_NOTE": {
		"en": "Crafting information about the selected item.",
		"de": "Herstellungsinformationen über das ausgewählte Element.",
		"es": "Información de elaboración sobre el objeto seleccionado.",
		"it": "Informazioni sulla creazione dell'oggetto selezionato.",
		"da": "Håndværksoplysninger om det valgte element.",
		"nl": "Maakinformatie over het geselecteerde item.",
		"fr": "Informations de fabrication sur l'objet sélectionné.",
		"tr": "Seçilen öğe hakkında üretim bilgileri.",
		"ko": "선택한 항목에 대한 제작 정보입니다.",
		"zh": "关于所选物品的制作信息。",
		"zh-TW": "關於所選物品的製作信息。",
		"ja": "選択したアイテムに関するクラフト情報。",
		"pt-BR": "Informações de fabricação sobre o item selecionado.",
		"ru": "Информация о создании выбранного предмета."
	}
}